{
    "home-manager": {
        "branch": "master",
        "description": "Manage a user environment using Nix  [maintainer=@rycee] ",
        "homepage": "https://nix-community.github.io/home-manager/",
        "owner": "nix-community",
        "repo": "home-manager",
        "rev": "48f2b381dd397ec88040d3354ac9c036739ba139",
        "sha256": "1i9v94brh9vhyhzcqyfj64nzhaibdj0sw74pxgk4bcsp0hqawgcd",
        "type": "tarball",
        "url": "https://github.com/nix-community/home-manager/archive/48f2b381dd397ec88040d3354ac9c036739ba139.tar.gz",
        "url_template": "https://github.com/<owner>/<repo>/archive/<rev>.tar.gz"
    },
    "niv": {
        "branch": "master",
        "description": "Easy dependency management for Nix projects",
        "homepage": "https://github.com/nmattia/niv",
        "owner": "nmattia",
        "repo": "niv",
        "rev": "5830a4dd348d77e39a0f3c4c762ff2663b602d4c",
        "sha256": "1d3lsrqvci4qz2hwjrcnd8h5vfkg8aypq3sjd4g3izbc8frwz5sm",
        "type": "tarball",
        "url": "https://github.com/nmattia/niv/archive/5830a4dd348d77e39a0f3c4c762ff2663b602d4c.tar.gz",
        "url_template": "https://github.com/<owner>/<repo>/archive/<rev>.tar.gz"
    },
    "nixpkgs": {
        "branch": "nixpkgs-unstable",
        "description": "Nix Packages collection",
        "homepage": "",
        "owner": "NixOS",
        "repo": "nixpkgs",
        "rev": "5c37ad87222cfc1ec36d6cd1364514a9efc2f7f2",
        "sha256": "1r74afnalgcbpv7b9sbdfbnx1kfj0kp1yfa60bbbv27n36vqdhbb",
        "type": "tarball",
        "url": "https://github.com/NixOS/nixpkgs/archive/5c37ad87222cfc1ec36d6cd1364514a9efc2f7f2.tar.gz",
        "url_template": "https://github.com/<owner>/<repo>/archive/<rev>.tar.gz"
    },
    "sops-nix": {
        "branch": "master",
        "description": "Atomic secret provisioning for NixOS based on sops",
        "homepage": "",
        "owner": "Mic92",
        "repo": "sops-nix",
        "rev": "afe00100b16648c1d79e62926caacac561df93a5",
        "sha256": "1dg3b5sl2idz1a58k2hb6qrprrhbvhm00lhi8fcjv3x224p80am3",
        "type": "tarball",
        "url": "https://github.com/Mic92/sops-nix/archive/afe00100b16648c1d79e62926caacac561df93a5.tar.gz",
        "url_template": "https://github.com/<owner>/<repo>/archive/<rev>.tar.gz"
    }
}
